shortcodes.py
shortcodes-5.4.0.dist-info/METADATA
shortcodes-5.4.0.dist-info/WHEEL
shortcodes-5.4.0.dist-info/top_level.txt
shortcodes-5.4.0.dist-info/RECORD
