Metadata-Version: 2.1
Name: shortcodes
Version: 5.4.0
Summary: A library for parsing customizable WordPress-style shortcodes.
Home-page: https://github.com/dmulholl/shortcodes
Author: Darren Mulholland
License: Public Domain
Platform: UNKNOWN
Classifier: Programming Language :: Python :: 3
Classifier: Development Status :: 5 - Production/Stable
Classifier: Operating System :: OS Independent
Classifier: License :: Public Domain
Classifier: Intended Audience :: Developers
Classifier: Topic :: Text Processing :: General
Requires-Python: >=3.6
